vikivission/Vission.py
vikivission/__init__.py
vikivision-1.0.0.dist-info/License.TXT
vikivision-1.0.0.dist-info/METADATA
vikivision-1.0.0.dist-info/WHEEL
vikivision-1.0.0.dist-info/top_level.txt
vikivision-1.0.0.dist-info/RECORD
