Metadata-Version: 2.1
Name: vikivision
Version: 1.0.0
Summary: An AI assistant that describes the live video feed from your camera.
Home-page: https://github.com/RMKEC111722203119/GenAI/tree/main/AI_EYE
Author: Vigneshwaran
Author-email: vign22112.it@rmkec.ac.in
License: MIT
Classifier: Programming Language :: Python :: 3
Classifier: License :: OSI Approved :: MIT License
Classifier: Operating System :: OS Independent
Requires-Python: >=3.6
License-File: License.TXT
Requires-Dist: opencv-python
Requires-Dist: google-generativeai
Requires-Dist: Pillow
Requires-Dist: pyttsx3
Requires-Dist: streamlit
